.gitignore
MANIFEST.in
README.txt
setup.cfg
setup.py
docs/HISTORY.txt
docs/LICENSE.GPL
docs/LICENSE.txt
gomobile/__init__.py
gomobile.convergence.egg-info/PKG-INFO
gomobile.convergence.egg-info/SOURCES.txt
gomobile.convergence.egg-info/dependency_links.txt
gomobile.convergence.egg-info/entry_points.txt
gomobile.convergence.egg-info/namespace_packages.txt
gomobile.convergence.egg-info/not-zip-safe
gomobile.convergence.egg-info/requires.txt
gomobile.convergence.egg-info/top_level.txt
gomobile/convergence/__init__.py
gomobile/convergence/behaviors.py
gomobile/convergence/filter.py
gomobile/convergence/indexing.py
gomobile/convergence/interfaces.py
gomobile/convergence/monkeypatch.py
gomobile/convergence/setuphandlers.py
gomobile/convergence/utilities.py
gomobile/convergence/browser/__init__.py
gomobile/convergence/browser/breadcrumbs.py
gomobile/convergence/browser/convergenceform.py
gomobile/convergence/browser/sitemap.py
gomobile/convergence/browser/tabs.py
gomobile/convergence/browser/views.py
gomobile/convergence/browser/portlets/__init__.py
gomobile/convergence/browser/portlets/media.py
gomobile/convergence/overrider/__init__.py
gomobile/convergence/overrider/base.py
gomobile/convergence/overrider/checker.py
gomobile/convergence/overrider/document.py
gomobile/convergence/tests/__init__.py
gomobile/convergence/tests/base.py
gomobile/convergence/tests/test_behavior.py
gomobile/convergence/tests/test_breadcrumbs.py
gomobile/convergence/tests/test_converged_content.py
gomobile/convergence/tests/test_mobile_overrides.py
gomobile/convergence/tests/test_sitemap.py
gomobile/convergence/tests/test_tabs.py
gomobile/convergence/tests/test_uninstall.py