Metadata-Version: 1.1
Name: gomobile.convergence
Version: 1.0.3
Summary: Multichannel content discrimination and overrides for Plone CMS
Home-page: http://webandmobile.mfabrik.com
Author: mFabrik Research Oy
Author-email: research@mfabrik.com
License: GPL
Keywords: mobile web cms plone zope applications apps iphone android
Platform: UNKNOWN
Classifier: Framework :: Plone
Classifier: Programming Language :: Python
Classifier: Topic :: Software Development :: Libraries :: Python Modules
